selectable/__init__.py
selectable/apps.py
selectable/base.py
selectable/decorators.py
selectable/exceptions.py
selectable/models.py
selectable/registry.py
selectable/urls.py
selectable/views.py
selectable/forms/__init__.py
selectable/forms/base.py
selectable/forms/fields.py
selectable/forms/widgets.py
selectable/locale/cs/LC_MESSAGES/django.mo
selectable/locale/cs/LC_MESSAGES/django.po
selectable/locale/de/LC_MESSAGES/django.mo
selectable/locale/de/LC_MESSAGES/django.po
selectable/locale/en/LC_MESSAGES/django.mo
selectable/locale/en/LC_MESSAGES/django.po
selectable/locale/es/LC_MESSAGES/django.mo
selectable/locale/es/LC_MESSAGES/django.po
selectable/locale/fr/LC_MESSAGES/django.mo
selectable/locale/fr/LC_MESSAGES/django.po
selectable/locale/it/LC_MESSAGES/django.mo
selectable/locale/it/LC_MESSAGES/django.po
selectable/locale/pl/LC_MESSAGES/django.mo
selectable/locale/pl/LC_MESSAGES/django.po
selectable/locale/pt_BR/LC_MESSAGES/django.mo
selectable/locale/pt_BR/LC_MESSAGES/django.po
selectable/locale/zh_CN/LC_MESSAGES/django.mo
selectable/locale/zh_CN/LC_MESSAGES/django.po
selectable/static/selectable/css/dj.selectable.css
selectable/static/selectable/js/jquery.dj.selectable.js
selectable/templates/selectable/jquery-css.html
selectable/templates/selectable/jquery-js.html
selectable/templatetags/__init__.py
selectable/templatetags/selectable_tags.py
selectable/tests/__init__.py
selectable/tests/base.py
selectable/tests/test_base.py
selectable/tests/test_decorators.py
selectable/tests/test_fields.py
selectable/tests/test_forms.py
selectable/tests/test_functional.py
selectable/tests/test_templatetags.py
selectable/tests/test_views.py
selectable/tests/test_widgets.py
selectable/tests/urls.py
selectable/tests/views.py
django_selectable-1.5.0.dist-info/AUTHORS.txt
django_selectable-1.5.0.dist-info/LICENSE.txt
django_selectable-1.5.0.dist-info/METADATA
django_selectable-1.5.0.dist-info/WHEEL
django_selectable-1.5.0.dist-info/top_level.txt
django_selectable-1.5.0.dist-info/RECORD
